hatlib/CMakeLists.txt.in
hatlib/__init__.py
hatlib/arg_info.py
hatlib/arg_value.py
hatlib/benchmark_hat_package.py
hatlib/callable_func.py
hatlib/cuda_loader.py
hatlib/function_info.py
hatlib/gpu_headers.py
hatlib/hat.py
hatlib/hat_file.py
hatlib/hat_package.py
hatlib/hat_to_dynamic.py
hatlib/hat_to_lib.py
hatlib/host_loader.py
hatlib/platform_utilities.py
hatlib/rocm_loader.py
hatlib/verify_hat_package.py
hatlib/pyhip/__init__.py
hatlib/pyhip/hip.py
hatlib/pyhip/hiprtc.py
hatlib-0.0.41.dist-info/LICENSE
hatlib-0.0.41.dist-info/METADATA
hatlib-0.0.41.dist-info/WHEEL
hatlib-0.0.41.dist-info/entry_points.txt
hatlib-0.0.41.dist-info/top_level.txt
hatlib-0.0.41.dist-info/RECORD
