Metadata-Version: 2.1
Name: hatlib
Version: 0.0.41
Summary: Tools for HAT (Header Annotated with TOML) packages
Home-page: https://www.github.com/microsoft/hat
Author: Microsoft Research AI Compilers Team
Author-email: mlodev@microsoft.com
Classifier: License :: OSI Approved :: MIT License
Classifier: Intended Audience :: Developers
Classifier: Topic :: Software Development
Classifier: Topic :: Software Development :: Libraries
Classifier: Topic :: Software Development :: Libraries :: Python Modules
Classifier: Programming Language :: C++
Classifier: Programming Language :: Python :: 3
Classifier: Programming Language :: Python :: 3.7
Classifier: Programming Language :: Python :: 3.8
Classifier: Programming Language :: Python :: 3.9
Classifier: Programming Language :: Python :: 3.10
Requires-Python: ~=3.7
License-File: LICENSE
Requires-Dist: numpy
Requires-Dist: pandas
Requires-Dist: toml
Requires-Dist: tomlkit
Requires-Dist: vswhere ; sys_platform == "win32"
